{
  "name": "ckeditor5",
  "title": "ckeditor5",
  "description": "The development environment of CKEditor 5 – the best browser-based rich text editor.",
  "author": {
    "name": "CKSource",
    "url": "http://cksource.com/"
  },
  "license": "GPL-2.0-or-later",
  "repository": {
    "type": "git",
    "url": "https://github.com/ckeditor/ckeditor5.git"
  },
  "homepage": "https://ckeditor.com/ckeditor-5",
  "npmName": "@ckeditor/ckeditor5-build-classic",
  "npmFileMap": [
    {
      "basePath": "build",
      "files": [
        "**/*.@(js|map)"
      ]
    }
  ],
  "filename": "ckeditor.min.js",
  "keywords": [
    "ckeditor",
    "ckeditor5",
    "ckeditor 5",
    "wysiwyg",
    "rich text",
    "editor",
    "html",
    "contentEditable",
    "editing",
    "operational transformation",
    "ot",
    "collaboration",
    "collaborative",
    "real-time",
    "framework"
  ]
}
