{
  "name": "clarity-ui",
  "filename": "clarity-ui.min.css",
  "description": "CSS for Clarity",
  "homepage": "https://vmware.github.io/clarity/",
  "repository": {
    "type": "git",
    "url": "git+https://github.com/vmware/clarity.git"
  },
  "keywords": [
    "ux",
    "ui",
    "css",
    "component-library",
    "design-system",
    "clarity"
  ],
  "license": "MIT",
  "autoupdate": {
    "source": "npm",
    "target": "clarity-ui",
    "fileMap": [
      {
        "basePath": "",
        "files": [
          "clarity-ui*"
        ]
      }
    ]
  },
  "authors": [
    {
      "name": "clarity"
    }
  ]
}
