{
  "name": "paver",
  "filename": "js/jquery.paver.min.js",
  "description": "A minimal panorama/image viewer replicating the effect seen in Facebook Pages app.",
  "homepage": "https://terrymun.github.io/paver/",
  "repository": {
    "type": "git",
    "url": "https://github.com/terrymun/paver/"
  },
  "keywords": [
    "paver",
    "panorama",
    "photo"
  ],
  "license": "MIT",
  "autoupdate": {
    "source": "git",
    "target": "git://github.com/terrymun/paver.git",
    "fileMap": [
      {
        "basePath": "dist",
        "files": [
          "**/*"
        ]
      },
      {
        "basePath": "src",
        "files": [
          "js/*paver*"
        ]
      }
    ]
  },
  "authors": [
    {
      "name": "Terry Mun",
      "email": "hello@terrymun.com",
      "url": "http://terrymun.com"
    }
  ]
}
