{
  "name": "datatables.net-rowreorder-bs",
  "description": "RowReorder for DataTables with styling for [Bootstrap 3](http://getbootstrap.com/)",
  "keywords": [
    "row reordering",
    "DataTables",
    "jQuery",
    "table",
    "Bootstrap"
  ],
  "license": "MIT",
  "homepage": "https://datatables.net",
  "repository": {
    "type": "git",
    "url": "git+https://github.com/DataTables/Dist-DataTables-RowReorder-Bootstrap.git"
  },
  "autoupdate": {
    "source": "npm",
    "target": "datatables.net-rowreorder-bs",
    "fileMap": [
      {
        "basePath": "css",
        "files": [
          "*.css"
        ]
      },
      {
        "basePath": "js",
        "files": [
          "*.js"
        ]
      }
    ]
  },
  "filename": "rowReorder.bootstrap.min.js",
  "authors": [
    {
      "name": "SpryMedia Ltd",
      "url": "http://datatables.net"
    }
  ]
}
