{
  "name": "domplotter",
  "description": "Minimalistic Virtual DOM implementation with support for animated transitions.",
  "homepage": "http://johan-gorter.github.io/domplotter/",
  "keywords": [
    "virtual",
    "dom",
    "animation",
    "transitions"
  ],
  "repository": {
    "type": "git",
    "url": "https://github.com/AFASSoftware/maquette"
  },
  "filename": "domplotter.min.js",
  "license": "MIT",
  "autoupdate": {
    "source": "npm",
    "target": "domplotter",
    "fileMap": [
      {
        "basePath": "dist",
        "files": [
          "*.js"
        ]
      }
    ]
  },
  "authors": [
    {
      "name": "Johan Gorter <johan@johangorter.com>"
    }
  ]
}
