{
  "name": "angular-ui-ace",
  "description": "This directive allows you to add ACE editor elements.",
  "keywords": [],
  "author": "https://github.com/angular-ui/ui-ace/graphs/contributors",
  "license": "MIT",
  "homepage": "http://angular-ui.github.com",
  "repository": {
    "type": "git",
    "url": "git://github.com/angular-ui/ui-ace.git"
  },
  "filename": "ui-ace.js",
  "autoupdate": {
    "source": "npm",
    "target": "angular-ui-ace",
    "fileMap": [
      {
        "basePath": "src",
        "files": [
          "*.js"
        ]
      }
    ]
  }
}
