{
  "name": "animejs",
  "description": "JavaScript animation engine",
  "filename": "anime.umd.min.js",
  "repository": {
    "type": "git",
    "url": "https://github.com/juliangarnier/anime.git"
  },
  "keywords": [
    "anime",
    "animejs",
    "anime.js",
    "timer",
    "animation",
    "timeline",
    "animatable",
    "draggable",
    "scope",
    "engine",
    "scroll",
    "easings",
    "cubic-bezier",
    "spring",
    "text",
    "JavaScript",
    "CSS",
    "SVG",
    "WAAPI",
    "Canvas",
    "WebGL"
  ],
  "license": "MIT",
  "homepage": "http://animejs.com",
  "autoupdate": {
    "source": "npm",
    "target": "animejs",
    "fileMap": [
      {
        "basePath": "dist/bundles",
        "files": [
          "*.min.js"
        ]
      }
    ]
  },
  "authors": [
    {
      "name": "Julian Garnier",
      "email": "julian@animejs.com"
    }
  ]
}
