{
  "name": "three.js",
  "filename": "three.min.js",
  "description": "JavaScript 3D library",
  "homepage": "http://threejs.org/",
  "keywords": [
    "3d",
    "WebGL"
  ],
  "autoupdate": {
    "source": "npm",
    "target": "three",
    "fileMap": [
      {
        "basePath": "build",
        "files": [
          "*.@(js|cjs)"
        ]
      }
    ]
  },
  "repository": {
    "type": "git",
    "url": "https://github.com/mrdoob/three.js.git"
  },
  "license": "MIT",
  "authors": [
    {
      "name": "mrdoob"
    }
  ]
}
