{
  "name": "embedly-jquery",
  "filename": "jquery.embedly.min.js",
  "description": "This library allows you to easily embed objects on any page.",
  "keywords": [
    "oEmbed",
    "jQuery",
    "embed"
  ],
  "license": "BSD-3-Clause",
  "repository": {
    "type": "git",
    "url": "https://github.com/embedly/embedly-jquery"
  },
  "authors": [
    {
      "name": "Art Gibson <art@embed.ly>"
    },
    {
      "name": "Sean Creeley <sean@embed.ly>"
    }
  ],
  "homepage": "https://embedly.github.io/embedly-jquery/",
  "autoupdate": {
    "source": "git",
    "target": "git://github.com/embedly/embedly-jquery.git",
    "fileMap": [
      {
        "basePath": "",
        "files": [
          "jquery.embedly*"
        ]
      }
    ]
  }
}
