{
  "name": "bootstrap-sweetalert",
  "description": "A beautiful 'replacement' for JavaScript's alert",
  "filename": "sweetalert.min.js",
  "homepage": "https://lipis.github.io/bootstrap-sweetalert/",
  "license": "MIT",
  "repository": {
    "type": "git",
    "url": "http://github.com/lipis/bootstrap-sweetalert"
  },
  "keywords": [
    "sweetalert",
    "alert",
    "modal",
    "popup"
  ],
  "autoupdate": {
    "source": "npm",
    "target": "bootstrap-sweetalert",
    "fileMap": [
      {
        "basePath": "dist",
        "files": [
          "**/*"
        ]
      }
    ]
  },
  "authors": [
    {
      "name": "Panayiotis Lipiridis <lipiridis@gmail.com>"
    }
  ]
}
