{
  "name": "motion-ui",
  "description": "Sass library for creating transitions and animations.",
  "filename": "motion-ui.min.js",
  "repository": {
    "type": "git",
    "url": "https://github.com/zurb/motion-ui.git"
  },
  "keywords": [
    "Sass",
    "motion"
  ],
  "author": {
    "name": "ZURB <foundation@zurb.com>"
  },
  "license": "MIT",
  "homepage": "http://zurb.com/playground/motion-ui",
  "autoupdate": {
    "source": "git",
    "target": "git://github.com/zurb/motion-ui.git",
    "fileMap": [
      {
        "basePath": "dist",
        "files": [
          "**/*"
        ]
      }
    ]
  }
}
