{
  "name": "goodshare.js",
  "filename": "goodshare.min.js",
  "description": "Useful modern JavaScript solution for share a link from your website to social networks or mobile messengers.",
  "keywords": [
    "share count",
    "social share",
    "social network share count",
    "share link"
  ],
  "homepage": "https://goodshare.js.org",
  "repository": {
    "type": "git",
    "url": "git+https://github.com/koddr/goodshare.js.git"
  },
  "license": "MIT",
  "autoupdate": {
    "source": "git",
    "target": "git://github.com/koddr/goodshare.js.git",
    "fileMap": [
      {
        "basePath": "",
        "files": [
          "goodshare*"
        ]
      }
    ]
  },
  "authors": [
    {
      "name": "Vic Shóstak"
    }
  ]
}
