{
  "name": "html5-device-mockups",
  "filename": "dist/device-mockups.min.css",
  "description": "HTML5 mockups of popular devices, to showcase your portfolio and spice up your website.",
  "keywords": [
    "html5",
    "device",
    "mockups",
    "demo",
    "portfolio"
  ],
  "repository": {
    "type": "git",
    "url": "https://github.com/pixelsign/html5-device-mockups.git"
  },
  "homepage": "https://pixelsign.github.io/html5-device-mockups/",
  "license": "MIT",
  "autoupdate": {
    "source": "git",
    "target": "https://github.com/pixelsign/html5-device-mockups.git",
    "fileMap": [
      {
        "basePath": "",
        "files": [
          "dist/**/*",
          "device-mockups/**/!(*.psd|*.ai)"
        ]
      }
    ]
  },
  "authors": [
    {
      "name": "Tomi Hiltunen"
    },
    {
      "name": "Angelos Arnis"
    },
    {
      "name": "Benjamin Bortels"
    }
  ]
}
