{
  "name": "ratchet",
  "filename": "js/ratchet.min.js",
  "description": "Build mobile apps with simple HTML, CSS, and JS components.",
  "keywords": [
    "mobile",
    "components"
  ],
  "autoupdate": {
    "source": "git",
    "target": "git://github.com/twbs/ratchet.git",
    "fileMap": [
      {
        "basePath": "dist",
        "files": [
          "**/*"
        ]
      }
    ]
  },
  "repository": {
    "type": "git",
    "url": "https://github.com/twbs/ratchet"
  },
  "license": "MIT",
  "authors": [
    {
      "name": "Connor Sears"
    }
  ]
}
