{
  "name": "lg-autoplay",
  "version": "1.0.4",
  "filename": "lg-autoplay.min.js",
  "description": "Autoplay module for lightgallery.",
  "keywords": [
    "gallery",
    "lightbox",
    "image",
    "youtube",
    "vimeo",
    "dailymotion",
    "html5 videos",
    "thumbnails",
    "zoom",
    "fullscreen",
    "responsive",
    "touch",
    "drag"
  ],
  "homepage": "https://sachinchoolur.github.io/lightGallery",
  "license": "GPL-3.0",
  "author": {
    "name": "Sachin N",
    "email": "sachi77n@gmail.com",
    "url": "https://github.com/sachinchoolur"
  },
  "repository": {
    "type": "git",
    "url": "https://github.com/sachinchoolur/lg-autoplay.git"
  },
  "autoupdate": {
    "source": "git",
    "target": "git://github.com/sachinchoolur/lg-autoplay.git",
    "fileMap": [
      {
        "basePath": "dist",
        "files": [
          "**/*"
        ]
      }
    ]
  }
}
