{
  "name": "seedrandom",
  "filename": "seedrandom.min.js",
  "keywords": [
    "random number",
    "seed"
  ],
  "description": "Seeded random number generator for Javascript.",
  "repository": {
    "type": "git",
    "url": "git://github.com/davidbau/seedrandom.git"
  },
  "license": "BSD",
  "autoupdate": {
    "source": "npm",
    "target": "seedrandom",
    "fileMap": [
      {
        "basePath": "",
        "files": [
          "seedrandom.js",
          "seedrandom.min.js",
          "lib/*"
        ]
      }
    ]
  },
  "authors": [
    {
      "name": "David Bau"
    }
  ]
}
