{
  "name": "slim-select",
  "description": "Slim vanilla javascript select dropdown",
  "filename": "slimselect.min.js",
  "homepage": "http://slimselectjs.com",
  "license": "MIT",
  "repository": {
    "type": "git",
    "url": "git+https://github.com/brianvoe/slim-select.git"
  },
  "keywords": [
    "select",
    "vanilla",
    "dropdown",
    "search"
  ],
  "autoupdate": {
    "source": "npm",
    "target": "slim-select",
    "fileMap": [
      {
        "basePath": "dist",
        "files": [
          "slimselect*"
        ]
      }
    ]
  },
  "authors": [
    {
      "name": "Brian Voelker",
      "email": "brian@webiswhatido.com",
      "url": "http://webiswhatido.com"
    }
  ]
}
